{
  "lockVersion": "1.0",
  "settings": {
    "resolveConflict": true,
    "resolveConflictStrict": false,
    "installAll": true
  },
  "overrides": {},
  "overrideDependencyMap": {},
  "modules": {
    ".": {
      "name": "",
      "dependencies": {},
      "devDependencies": {},
      "dynamicDependencies": {},
      "maskedByOverrideDependencyMap": false
    },
    "entry": {
      "name": "entry",
      "dependencies": {
        "libautel_sdk.so": {
          "specifier": "file:entry/src/main/cpp/types/libautel_sdk",
          "version": "file:entry/src/main/cpp/types/libautel_sdk"
        }
      },
      "devDependencies": {},
      "dynamicDependencies": {},
      "maskedByOverrideDependencyMap": false
    }
  },
  "packages": {
    "libautel_sdk.so@file:entry/src/main/cpp/types/libautel_sdk": {
      "storePath": "entry/src/main/cpp/types/libautel_sdk",
      "dependencies": {},
      "dynamicDependencies": {},
      "dev": false,
      "dynamic": false,
      "maskedByOverrideDependencyMap": false
    }
  }
}